VirtualCollegeAPIWrapper/Columns.py
VirtualCollegeAPIWrapper/VirtualCollege.py
virtualcollegeapiwrapper-0.1.6.dist-info/METADATA
virtualcollegeapiwrapper-0.1.6.dist-info/WHEEL
virtualcollegeapiwrapper-0.1.6.dist-info/RECORD
